aukpy/__init__.py
aukpy/config.py
aukpy/db.py
aukpy/queries.py
tests/__init__.py
tests/db_test.py
tests/gen_mock_data.py
tests/perf_test.py
tests/queries_test.py
tests/rebuild_test.py
aukpy-1.0.0.dist-info/LICENSE
aukpy-1.0.0.dist-info/METADATA
aukpy-1.0.0.dist-info/WHEEL
aukpy-1.0.0.dist-info/top_level.txt
aukpy-1.0.0.dist-info/RECORD
