Metadata-Version: 2.1
Name: aukpy
Version: 1.0.0
Summary: Reimplementation of auk in Python
Author-email: Vincent Luczkow <vincent.luczkow@gmail.com>
License: MIT License        
Project-URL: Homepage, https://github.com/vluzko/aukpy
Project-URL: Bug Tracker, https://github.com/vluzko/aukpy/issues
Classifier: Programming Language :: Python :: 3
Classifier: License :: OSI Approved :: MIT License
Classifier: Operating System :: OS Independent
Requires-Python: >=3.6
License-File: LICENSE
Requires-Dist: numpy (==1.23.1)
Requires-Dist: pandas (==1.4.3)
Provides-Extra: docs
Requires-Dist: Sphinx (==5.1.1) ; extra == 'docs'
Requires-Dist: sphinx-rtd-theme (==1.0.0) ; extra == 'docs'
Provides-Extra: tests
Requires-Dist: black (==22.6.0) ; extra == 'tests'
Requires-Dist: pytest (==7.1.2) ; extra == 'tests'
Requires-Dist: mypy (==0.971) ; extra == 'tests'
Requires-Dist: pandas-stubs (==1.4.3.220807) ; extra == 'tests'
